mapjoin
