Metadata-Version: 2.1
Name: mapjoin
Version: 0.2.0
Summary: the OBSCENE string generation one-liner
Home-page: https://yourlabs.io/oss/mapjoin
License: UNKNOWN
Keywords: automation cli
Platform: UNKNOWN
Requires-Python: >=3
